README.md
django_fly.py
setup.py
django_fly.egg-info/PKG-INFO
django_fly.egg-info/SOURCES.txt
django_fly.egg-info/dependency_links.txt
django_fly.egg-info/entry_points.txt
django_fly.egg-info/requires.txt
django_fly.egg-info/top_level.txt