Metadata-Version: 1.1
Name: django-fly
Version: 0.0.4
Summary: UNKNOWN
Home-page: https://github.com/LehaoLin/django-fly
Author: Lehao Lin
Author-email: lehaolin@link.cuhk.edu.cn
License: MIT
Platform: UNKNOWN
Classifier: Programming Language :: Python
Classifier: Programming Language :: Python :: Implementation
Classifier: Programming Language :: Python :: 3
Classifier: Topic :: Software Development :: Libraries
